{
  "@context": [
    "{{base}}/contexts/neurosciencegraph/core/schema/v0.1.0",
    {
      "this": "{{base}}/schemas/neurosciencegraph/simulation/bluepyefeconfiguration/v0.1.0/shapes/"
    }
  ],
  "@type": "nxv:Schema",
  "imports": [
    "{{base}}/schemas/neurosciencegraph/simulation/modelinstance/v0.1.0",
    "{{base}}/schemas/neurosciencegraph/simulation/modelscript/v0.1.0"
  ],
  "shapes": [
    {
      "@id": "this:BluePyEfeConfigurationShape",
      "@type": "sh:NodeShape",
      "label": "BluePyEfe specific configuration shape",
      "comment": "BluePyEfe specific efeature extraction configuration shape.",
      "editorialNote": "Files are in github repo.",
      "targetClass": "nsg:Configuration",
      "nodekind": "sh:BlankNodeOrIRI",
      "and": [
        {
          "node": "{{base}}/schemas/neurosciencegraph/commons/entity/v0.1.0/shapes/EntityShape"
        },
        {
          "property": [
            {
              "path": "schema:distribution",
              "name": "Configuration file (s)",
              "description": "Link to the configuration files. Note that the minCount=1 constraint forces the config files not be necessarily stored in Nexus.",
              "minCount": 1,
              "maxCount": 1
            }
          ]
        }
      ]
    }
  ]
}